app_generator/__init__.py
app_generator/generate_django_app.py
django_custom_appgen-0.1.dist-info/METADATA
django_custom_appgen-0.1.dist-info/WHEEL
django_custom_appgen-0.1.dist-info/entry_points.txt
django_custom_appgen-0.1.dist-info/top_level.txt
django_custom_appgen-0.1.dist-info/RECORD
