Metadata-Version: 2.4
Name: django-custom-appgen
Version: 0.1
Summary: Générateur d'app Django avec structure personnalisée
Home-page: https://github.com/kellykomenan/django-custom-appgen
Author: kelly
License: MIT
Classifier: Programming Language :: Python :: 3
Classifier: Framework :: Django
Classifier: License :: OSI Approved :: MIT License
Classifier: Operating System :: OS Independent
Requires-Python: >=3.6
Dynamic: author
Dynamic: classifier
Dynamic: description
Dynamic: description-content-type
Dynamic: home-page
Dynamic: license
Dynamic: requires-python
Dynamic: summary
